plasmasaver/plasmasaver.py
plasmasaver-1.0.1.dist-info/LICENSE
plasmasaver-1.0.1.dist-info/METADATA
plasmasaver-1.0.1.dist-info/WHEEL
plasmasaver-1.0.1.dist-info/entry_points.txt
plasmasaver-1.0.1.dist-info/top_level.txt
plasmasaver-1.0.1.dist-info/RECORD
