Metadata-Version: 2.1
Name: plasmasaver
Version: 1.0.1
Summary: Command Line Interface to manage(save, export, import) KDE Plasma settings/configs in form of profile.
Author-email: Pankaj Jackson <pankajackson@live.co.uk>
License: GNU GENERAL PUBLIC LICENSE
Project-URL: Homepage, https://github.com/pankajackson/plasmasaver
Project-URL: Bug Tracker, https://github.com/pankajackson/plasmasaver/issues
Project-URL: Source, https://github.com/pankajackson/plasmasaver
Keywords: kde,plasma,config,setting,settings,save,saver
Classifier: Programming Language :: Python :: 3
Classifier: Development Status :: 5 - Production/Stable
Classifier: Intended Audience :: End Users/Desktop
Classifier: License :: OSI Approved :: GNU General Public License v3 or later (GPLv3+)
Classifier: Operating System :: Unix
Requires-Python: >=3.7
License-File: LICENSE
Requires-Dist: PyYAML
